JCer/__init__.py
JCer/client.py
JCer/server.py
JCer/static/css/font-awesome.min.css
JCer/static/js/tailwind.js
JCer/static/webfonts/fa-solid-900.ttf
JCer/static/webfonts/fa-solid-900.woff2
jcer-0.4.3.dist-info/licenses/LICENSE
jcer-0.4.3.dist-info/METADATA
jcer-0.4.3.dist-info/WHEEL
jcer-0.4.3.dist-info/entry_points.txt
jcer-0.4.3.dist-info/top_level.txt
jcer-0.4.3.dist-info/RECORD
