Metadata-Version: 2.4
Name: JCer
Version: 0.4.3
Summary: A package for remote control with screen capture and input handling
Author: YANGRENRUIYRR
Author-email: yangrenruiyrr@yeah.net
Classifier: Programming Language :: Python :: 3.6
Classifier: Programming Language :: Python :: 3.7
Classifier: Programming Language :: Python :: 3.8
Classifier: License :: OSI Approved :: MIT License
Classifier: Operating System :: OS Independent
Classifier: Topic :: Software Development :: Libraries :: Python Modules
Classifier: Topic :: Utilities
Requires-Python: >=3.6
License-File: LICENSE
Provides-Extra: client
Requires-Dist: certifi>=2025.4.26; extra == "client"
Requires-Dist: charset-normalizer>=2.0.0; extra == "client"
Requires-Dist: idna>=3.10; extra == "client"
Requires-Dist: ipaddress>=1.0.23; extra == "client"
Requires-Dist: mss>=7.0.1; extra == "client"
Requires-Dist: pillow>=8.4.0; extra == "client"
Requires-Dist: pynput>=1.8.1; extra == "client"
Requires-Dist: requests>=2.27.1; extra == "client"
Requires-Dist: six>=1.17.0; extra == "client"
Requires-Dist: urllib3>=1.26.20; extra == "client"
Provides-Extra: server
Requires-Dist: blinker>=1.5; extra == "server"
Requires-Dist: click>=7.1.2; extra == "server"
Requires-Dist: colorama>=0.4.5; extra == "server"
Requires-Dist: Flask>=1.1.4; extra == "server"
Requires-Dist: itsdangerous>=1.1.0; extra == "server"
Requires-Dist: Jinja2>=2.11.3; extra == "server"
Requires-Dist: MarkupSafe>=2.0.1; extra == "server"
Requires-Dist: pyotp>=2.7.0; extra == "server"
Requires-Dist: waitress>=2.0.0; extra == "server"
Requires-Dist: Werkzeug>=1.0.1; extra == "server"
Provides-Extra: all
Requires-Dist: blinker>=1.5; extra == "all"
Requires-Dist: click>=7.1.2; extra == "all"
Requires-Dist: colorama>=0.4.5; extra == "all"
Requires-Dist: Flask>=1.1.4; extra == "all"
Requires-Dist: itsdangerous>=1.1.0; extra == "all"
Requires-Dist: Jinja2>=2.11.3; extra == "all"
Requires-Dist: MarkupSafe>=2.0.1; extra == "all"
Requires-Dist: pyotp>=2.7.0; extra == "all"
Requires-Dist: waitress>=2.0.0; extra == "all"
Requires-Dist: Werkzeug>=1.0.1; extra == "all"
Requires-Dist: certifi>=2025.4.26; extra == "all"
Requires-Dist: charset-normalizer>=2.0.0; extra == "all"
Requires-Dist: idna>=3.10; extra == "all"
Requires-Dist: ipaddress>=1.0.23; extra == "all"
Requires-Dist: mss>=7.0.1; extra == "all"
Requires-Dist: pillow>=8.4.0; extra == "all"
Requires-Dist: pynput>=1.8.1; extra == "all"
Requires-Dist: requests>=2.27.1; extra == "all"
Requires-Dist: six>=1.17.0; extra == "all"
Requires-Dist: urllib3>=1.26.20; extra == "all"
Requires-Dist: certifi==2025.4.26; python_version == "3.6" and extra == "client"
Requires-Dist: charset-normalizer==2.0.0; python_version == "3.6" and extra == "client"
Requires-Dist: idna==3.10; python_version == "3.6" and extra == "client"
Requires-Dist: ipaddress==1.0.23; python_version == "3.6" and extra == "client"
Requires-Dist: mss==7.0.1; python_version == "3.6" and extra == "client"
Requires-Dist: Pillow==8.4.0; python_version == "3.6" and extra == "client"
Requires-Dist: pynput==1.8.1; python_version == "3.6" and extra == "client"
Requires-Dist: requests==2.27.1; python_version == "3.6" and extra == "client"
Requires-Dist: six==1.17.0; python_version == "3.6" and extra == "client"
Requires-Dist: urllib3==1.26.20; python_version == "3.6" and extra == "client"
Requires-Dist: blinker==1.5; python_version == "3.6" and extra == "server"
Requires-Dist: click==7.1.2; python_version == "3.6" and extra == "server"
Requires-Dist: colorama==0.4.5; python_version == "3.6" and extra == "server"
Requires-Dist: dataclasses==0.8; python_version == "3.6" and extra == "server"
Requires-Dist: Flask==1.1.4; python_version == "3.6" and extra == "server"
Requires-Dist: importlib-metadata==4.8.3; python_version == "3.6" and extra == "server"
Requires-Dist: itsdangerous==1.1.0; python_version == "3.6" and extra == "server"
Requires-Dist: Jinja2==2.11.3; python_version == "3.6" and extra == "server"
Requires-Dist: MarkupSafe==2.0.1; python_version == "3.6" and extra == "server"
Requires-Dist: pyotp==2.7.0; python_version == "3.6" and extra == "server"
Requires-Dist: typing-extensions==4.1.1; python_version == "3.6" and extra == "server"
Requires-Dist: waitress==2.0.0; python_version == "3.6" and extra == "server"
Requires-Dist: Werkzeug==1.0.1; python_version == "3.6" and extra == "server"
Requires-Dist: zipp==3.6.0; python_version == "3.6" and extra == "server"
Requires-Dist: blinker==1.5; python_version == "3.6" and extra == "all"
Requires-Dist: click==7.1.2; python_version == "3.6" and extra == "all"
Requires-Dist: colorama==0.4.5; python_version == "3.6" and extra == "all"
Requires-Dist: dataclasses==0.8; python_version == "3.6" and extra == "all"
Requires-Dist: Flask==1.1.4; python_version == "3.6" and extra == "all"
Requires-Dist: importlib-metadata==4.8.3; python_version == "3.6" and extra == "all"
Requires-Dist: itsdangerous==1.1.0; python_version == "3.6" and extra == "all"
Requires-Dist: Jinja2==2.11.3; python_version == "3.6" and extra == "all"
Requires-Dist: MarkupSafe==2.0.1; python_version == "3.6" and extra == "all"
Requires-Dist: pyotp==2.7.0; python_version == "3.6" and extra == "all"
Requires-Dist: typing-extensions==4.1.1; python_version == "3.6" and extra == "all"
Requires-Dist: waitress==2.0.0; python_version == "3.6" and extra == "all"
Requires-Dist: Werkzeug==1.0.1; python_version == "3.6" and extra == "all"
Requires-Dist: zipp==3.6.0; python_version == "3.6" and extra == "all"
Requires-Dist: certifi==2025.4.26; python_version == "3.6" and extra == "all"
Requires-Dist: charset-normalizer==2.0.0; python_version == "3.6" and extra == "all"
Requires-Dist: idna==3.10; python_version == "3.6" and extra == "all"
Requires-Dist: ipaddress==1.0.23; python_version == "3.6" and extra == "all"
Requires-Dist: mss==7.0.1; python_version == "3.6" and extra == "all"
Requires-Dist: Pillow==8.4.0; python_version == "3.6" and extra == "all"
Requires-Dist: pynput==1.8.1; python_version == "3.6" and extra == "all"
Requires-Dist: requests==2.27.1; python_version == "3.6" and extra == "all"
Requires-Dist: six==1.17.0; python_version == "3.6" and extra == "all"
Requires-Dist: urllib3==1.26.20; python_version == "3.6" and extra == "all"
Requires-Dist: certifi==2025.4.26; python_version == "3.7" and extra == "client"
Requires-Dist: charset-normalizer==2.0.0; python_version == "3.7" and extra == "client"
Requires-Dist: idna==3.10; python_version == "3.7" and extra == "client"
Requires-Dist: ipaddress==1.0.23; python_version == "3.7" and extra == "client"
Requires-Dist: mss==7.0.1; python_version == "3.7" and extra == "client"
Requires-Dist: Pillow==8.4.0; python_version == "3.7" and extra == "client"
Requires-Dist: pynput==1.8.1; python_version == "3.7" and extra == "client"
Requires-Dist: requests==2.27.1; python_version == "3.7" and extra == "client"
Requires-Dist: six==1.17.0; python_version == "3.7" and extra == "client"
Requires-Dist: urllib3==1.26.20; python_version == "3.7" and extra == "client"
Requires-Dist: blinker==1.5; python_version == "3.7" and extra == "server"
Requires-Dist: click==7.1.2; python_version == "3.7" and extra == "server"
Requires-Dist: colorama==0.4.5; python_version == "3.7" and extra == "server"
Requires-Dist: Flask==1.1.4; python_version == "3.7" and extra == "server"
Requires-Dist: importlib-metadata==4.8.3; python_version == "3.7" and extra == "server"
Requires-Dist: itsdangerous==1.1.0; python_version == "3.7" and extra == "server"
Requires-Dist: Jinja2==2.11.3; python_version == "3.7" and extra == "server"
Requires-Dist: MarkupSafe==2.0.1; python_version == "3.7" and extra == "server"
Requires-Dist: pyotp==2.7.0; python_version == "3.7" and extra == "server"
Requires-Dist: typing-extensions==4.1.1; python_version == "3.7" and extra == "server"
Requires-Dist: waitress==2.0.0; python_version == "3.7" and extra == "server"
Requires-Dist: Werkzeug==1.0.1; python_version == "3.7" and extra == "server"
Requires-Dist: zipp==3.6.0; python_version == "3.7" and extra == "server"
Requires-Dist: blinker==1.5; python_version == "3.7" and extra == "all"
Requires-Dist: click==7.1.2; python_version == "3.7" and extra == "all"
Requires-Dist: colorama==0.4.5; python_version == "3.7" and extra == "all"
Requires-Dist: Flask==1.1.4; python_version == "3.7" and extra == "all"
Requires-Dist: importlib-metadata==4.8.3; python_version == "3.7" and extra == "all"
Requires-Dist: itsdangerous==1.1.0; python_version == "3.7" and extra == "all"
Requires-Dist: Jinja2==2.11.3; python_version == "3.7" and extra == "all"
Requires-Dist: MarkupSafe==2.0.1; python_version == "3.7" and extra == "all"
Requires-Dist: pyotp==2.7.0; python_version == "3.7" and extra == "all"
Requires-Dist: typing-extensions==4.1.1; python_version == "3.7" and extra == "all"
Requires-Dist: waitress==2.0.0; python_version == "3.7" and extra == "all"
Requires-Dist: Werkzeug==1.0.1; python_version == "3.7" and extra == "all"
Requires-Dist: zipp==3.6.0; python_version == "3.7" and extra == "all"
Requires-Dist: certifi==2025.4.26; python_version == "3.7" and extra == "all"
Requires-Dist: charset-normalizer==2.0.0; python_version == "3.7" and extra == "all"
Requires-Dist: idna==3.10; python_version == "3.7" and extra == "all"
Requires-Dist: ipaddress==1.0.23; python_version == "3.7" and extra == "all"
Requires-Dist: mss==7.0.1; python_version == "3.7" and extra == "all"
Requires-Dist: Pillow==8.4.0; python_version == "3.7" and extra == "all"
Requires-Dist: pynput==1.8.1; python_version == "3.7" and extra == "all"
Requires-Dist: requests==2.27.1; python_version == "3.7" and extra == "all"
Requires-Dist: six==1.17.0; python_version == "3.7" and extra == "all"
Requires-Dist: urllib3==1.26.20; python_version == "3.7" and extra == "all"
Requires-Dist: certifi==2025.4.26; python_version == "3.8" and extra == "client"
Requires-Dist: charset-normalizer==2.0.0; python_version == "3.8" and extra == "client"
Requires-Dist: idna==3.10; python_version == "3.8" and extra == "client"
Requires-Dist: ipaddress==1.0.23; python_version == "3.8" and extra == "client"
Requires-Dist: mss==7.0.1; python_version == "3.8" and extra == "client"
Requires-Dist: Pillow==8.4.0; python_version == "3.8" and extra == "client"
Requires-Dist: pynput==1.8.1; python_version == "3.8" and extra == "client"
Requires-Dist: requests==2.27.1; python_version == "3.8" and extra == "client"
Requires-Dist: six==1.17.0; python_version == "3.8" and extra == "client"
Requires-Dist: urllib3==1.26.20; python_version == "3.8" and extra == "client"
Requires-Dist: blinker==1.5; python_version == "3.8" and extra == "server"
Requires-Dist: click==7.1.2; python_version == "3.8" and extra == "server"
Requires-Dist: colorama==0.4.5; python_version == "3.8" and extra == "server"
Requires-Dist: Flask==1.1.4; python_version == "3.8" and extra == "server"
Requires-Dist: importlib-metadata==4.8.3; python_version == "3.8" and extra == "server"
Requires-Dist: itsdangerous==1.1.0; python_version == "3.8" and extra == "server"
Requires-Dist: Jinja2==2.11.3; python_version == "3.8" and extra == "server"
Requires-Dist: MarkupSafe==2.0.1; python_version == "3.8" and extra == "server"
Requires-Dist: pyotp==2.7.0; python_version == "3.8" and extra == "server"
Requires-Dist: typing-extensions==4.1.1; python_version == "3.8" and extra == "server"
Requires-Dist: waitress==2.0.0; python_version == "3.8" and extra == "server"
Requires-Dist: Werkzeug==1.0.1; python_version == "3.8" and extra == "server"
Requires-Dist: zipp==3.6.0; python_version == "3.8" and extra == "server"
Requires-Dist: blinker==1.5; python_version == "3.8" and extra == "all"
Requires-Dist: click==7.1.2; python_version == "3.8" and extra == "all"
Requires-Dist: colorama==0.4.5; python_version == "3.8" and extra == "all"
Requires-Dist: Flask==1.1.4; python_version == "3.8" and extra == "all"
Requires-Dist: importlib-metadata==4.8.3; python_version == "3.8" and extra == "all"
Requires-Dist: itsdangerous==1.1.0; python_version == "3.8" and extra == "all"
Requires-Dist: Jinja2==2.11.3; python_version == "3.8" and extra == "all"
Requires-Dist: MarkupSafe==2.0.1; python_version == "3.8" and extra == "all"
Requires-Dist: pyotp==2.7.0; python_version == "3.8" and extra == "all"
Requires-Dist: typing-extensions==4.1.1; python_version == "3.8" and extra == "all"
Requires-Dist: waitress==2.0.0; python_version == "3.8" and extra == "all"
Requires-Dist: Werkzeug==1.0.1; python_version == "3.8" and extra == "all"
Requires-Dist: zipp==3.6.0; python_version == "3.8" and extra == "all"
Requires-Dist: certifi==2025.4.26; python_version == "3.8" and extra == "all"
Requires-Dist: charset-normalizer==2.0.0; python_version == "3.8" and extra == "all"
Requires-Dist: idna==3.10; python_version == "3.8" and extra == "all"
Requires-Dist: ipaddress==1.0.23; python_version == "3.8" and extra == "all"
Requires-Dist: mss==7.0.1; python_version == "3.8" and extra == "all"
Requires-Dist: Pillow==8.4.0; python_version == "3.8" and extra == "all"
Requires-Dist: pynput==1.8.1; python_version == "3.8" and extra == "all"
Requires-Dist: requests==2.27.1; python_version == "3.8" and extra == "all"
Requires-Dist: six==1.17.0; python_version == "3.8" and extra == "all"
Requires-Dist: urllib3==1.26.20; python_version == "3.8" and extra == "all"
Dynamic: author
Dynamic: author-email
Dynamic: classifier
Dynamic: description
Dynamic: description-content-type
Dynamic: license-file
Dynamic: provides-extra
Dynamic: requires-python
Dynamic: summary
